odoo/addons/stay_report_py3o/README.rst
odoo/addons/stay_report_py3o/__init__.py
odoo/addons/stay_report_py3o/__manifest__.py
odoo/addons/stay_report_py3o/report.xml
odoo/addons/stay_report_py3o/stay_arrival.odt
odoo/addons/stay_report_py3o/stay_journal.odt
odoo/addons/stay_report_py3o/stay_meal.odt
odoo/addons/stay_report_py3o/stay_toclean.odt
odoo/addons/stay_report_py3o/i18n/it.po
odoo/addons/stay_report_py3o/i18n/stay_report_py3o.pot
odoo/addons/stay_report_py3o/readme/CONTRIBUTORS.rst
odoo/addons/stay_report_py3o/readme/DESCRIPTION.rst
odoo/addons/stay_report_py3o/static/description/icon.png
odoo/addons/stay_report_py3o/static/description/index.html
odoo_addon_stay_report_py3o-16.0.1.0.0.4.dist-info/METADATA
odoo_addon_stay_report_py3o-16.0.1.0.0.4.dist-info/WHEEL
odoo_addon_stay_report_py3o-16.0.1.0.0.4.dist-info/top_level.txt
odoo_addon_stay_report_py3o-16.0.1.0.0.4.dist-info/RECORD
