Metadata-Version: 2.1
Name: odoo-addon-stay-report-py3o
Version: 16.0.1.0.0.4
Summary: Replace Qweb report by Py3o report on stay module
Home-page: https://github.com/OCA/vertical-abbey
Author: Barroux Abbey, Akretion, Odoo Community Association (OCA)
Author-email: support@odoo-community.org
License: AGPL-3
Platform: UNKNOWN
Classifier: Programming Language :: Python
Classifier: Framework :: Odoo
Classifier: Framework :: Odoo :: 16.0
Classifier: License :: OSI Approved :: GNU Affero General Public License v3
Requires-Python: >=3.10
Requires-Dist: odoo-addon-report-py3o <16.1dev,>=16.0dev
Requires-Dist: odoo-addon-stay <16.1dev,>=16.0dev
Requires-Dist: odoo <16.1dev,>=16.0a
